weitersager/__init__.py
weitersager/cli.py
weitersager/config.py
weitersager/http.py
weitersager/irc.py
weitersager/processor.py
weitersager/signals.py
weitersager/tokencli.py
weitersager/util.py
weitersager-1.0.1.dist-info/METADATA
weitersager-1.0.1.dist-info/WHEEL
weitersager-1.0.1.dist-info/entry_points.txt
weitersager-1.0.1.dist-info/licenses/LICENSE
weitersager-1.0.1.dist-info/RECORD
