Metadata-Version: 2.4
Name: Weitersager
Version: 1.0.1
Summary: A proxy to forward messages received via HTTP to IRC
Project-URL: Changelog, https://github.com/homeworkprod/weitersager/blob/main/CHANGES.rst
Project-URL: Homepage, https://homework.nwsnet.de/releases/1cda/#weitersager
Project-URL: Source code, https://github.com/homeworkprod/weitersager
Author-email: Jochen Kupperschmidt <homework@nwsnet.de>
License-Expression: MIT
License-File: LICENSE
Keywords: irc,webhook
Classifier: Development Status :: 5 - Production/Stable
Classifier: Intended Audience :: Developers
Classifier: Intended Audience :: Other Audience
Classifier: Intended Audience :: System Administrators
Classifier: License :: OSI Approved :: MIT License
Classifier: Operating System :: OS Independent
Classifier: Programming Language :: Python
Classifier: Programming Language :: Python :: 3
Classifier: Programming Language :: Python :: 3.9
Classifier: Programming Language :: Python :: 3.10
Classifier: Programming Language :: Python :: 3.11
Classifier: Programming Language :: Python :: 3.12
Classifier: Programming Language :: Python :: 3.13
Classifier: Topic :: Communications :: Chat :: Internet Relay Chat
Classifier: Topic :: Internet :: WWW/HTTP
Classifier: Topic :: System :: Logging
Classifier: Topic :: System :: Systems Administration
Classifier: Topic :: Utilities
Requires-Python: >=3.9
Requires-Dist: blinker>=1.9.0
Requires-Dist: irc>=20.5.0
Requires-Dist: rtoml>=0.12.0
Requires-Dist: werkzeug>=3.1.3
